cloudburst_fargate/__init__.py
cloudburst_fargate/fargate_operation.py
cloudburst_fargate/version.py
cloudburst_fargate-1.0.1.dist-info/licenses/LICENSE
cloudburst_fargate-1.0.1.dist-info/METADATA
cloudburst_fargate-1.0.1.dist-info/WHEEL
cloudburst_fargate-1.0.1.dist-info/top_level.txt
cloudburst_fargate-1.0.1.dist-info/RECORD
