Metadata-Version: 2.4
Name: cloudburst-fargate
Version: 1.0.1
Summary: Serverless video processing using AWS ECS Fargate
Home-page: https://github.com/preangelleo/cloudburst-fargate
Author: Leo Wang
Author-email: Leo Wang <me@leowang.net>
License: MIT
Project-URL: Homepage, https://github.com/preangelleo/cloudburst-fargate
Project-URL: Documentation, https://github.com/preangelleo/cloudburst-fargate/blob/main/README.md
Project-URL: Repository, https://github.com/preangelleo/cloudburst-fargate.git
Project-URL: Bug Tracker, https://github.com/preangelleo/cloudburst-fargate/issues
Classifier: Development Status :: 5 - Production/Stable
Classifier: Intended Audience :: Developers
Classifier: Topic :: Software Development :: Libraries :: Python Modules
Classifier: Topic :: Multimedia :: Video
Classifier: License :: OSI Approved :: MIT License
Classifier: Programming Language :: Python :: 3
Classifier: Programming Language :: Python :: 3.7
Classifier: Programming Language :: Python :: 3.8
Classifier: Programming Language :: Python :: 3.9
Classifier: Programming Language :: Python :: 3.10
Classifier: Programming Language :: Python :: 3.11
Classifier: Operating System :: OS Independent
Requires-Python: >=3.7
License-File: LICENSE
Requires-Dist: boto3>=1.26.0
Requires-Dist: requests>=2.28.0
Requires-Dist: python-dotenv>=0.19.0
Requires-Dist: colorama>=0.4.4
Provides-Extra: dev
Requires-Dist: pytest>=6.0; extra == "dev"
Requires-Dist: pytest-cov>=2.0; extra == "dev"
Requires-Dist: black>=22.0; extra == "dev"
Requires-Dist: flake8>=4.0; extra == "dev"
Dynamic: author
Dynamic: home-page
Dynamic: license-file
Dynamic: requires-python
